my_dsa_yogi/__init__.py
my_dsa_yogi-0.1.0.dist-info/METADATA
my_dsa_yogi-0.1.0.dist-info/WHEEL
my_dsa_yogi-0.1.0.dist-info/RECORD
