Metadata-Version: 2.3
Name: my-dsa-yogi
Version: 0.1.0
Summary: 
Author: yogi
Author-email: yogisingh580@gmail.com
Requires-Python: >=3.9
Classifier: Programming Language :: Python :: 3
Classifier: Programming Language :: Python :: 3.9
Classifier: Programming Language :: Python :: 3.10
Classifier: Programming Language :: Python :: 3.11
Classifier: Programming Language :: Python :: 3.12
Classifier: Programming Language :: Python :: 3.13
Requires-Dist: black (>=25.1.0,<26.0.0)
Requires-Dist: pendulum (>=3.1.0,<4.0.0)
